HologramAuth/HOTPAuthentication.py
HologramAuth/Holohash.py
HologramAuth/SIMOTPAuthentication.py
HologramAuth/TOTPAuthentication.py
HologramAuth/__init__.py
python_sdk_auth-0.4.0.dist-info/AUTHORS
python_sdk_auth-0.4.0.dist-info/LICENSE
python_sdk_auth-0.4.0.dist-info/METADATA
python_sdk_auth-0.4.0.dist-info/WHEEL
python_sdk_auth-0.4.0.dist-info/top_level.txt
python_sdk_auth-0.4.0.dist-info/RECORD
